xconfig/__init__.py
xconfig/__main__.py
xconfig-0.0.5.dist-info/LICENSE
xconfig-0.0.5.dist-info/METADATA
xconfig-0.0.5.dist-info/WHEEL
xconfig-0.0.5.dist-info/top_level.txt
xconfig-0.0.5.dist-info/RECORD
