Metadata-Version: 2.1
Name: xconfig
Version: 0.0.5
Summary: yaml config for python
Home-page: https://github.com/remorses/TODO
Author: Tommaso De Rossi
Author-email: daer.tommy@gmail.com
License: Apache Software License 2.0
Keywords: xconfig,config,yaml
Platform: UNKNOWN
Classifier: Intended Audience :: Information Technology
Classifier: Programming Language :: Python :: 3
Classifier: Programming Language :: Python :: 3.6
Classifier: Programming Language :: Python :: 3.7
Requires-Dist: pyyaml
Requires-Dist: aiofiles
